library_and_tools/__init__.py
library_and_tools/jsonLib.py
library_and_tools/osLib.py
library_and_tools/randomLib.py
library_and_tools/timeLib.py
library_and_tools/turtleLib.py
library_and_tools-1.0.0.dist-info/METADATA
library_and_tools-1.0.0.dist-info/WHEEL
library_and_tools-1.0.0.dist-info/top_level.txt
library_and_tools-1.0.0.dist-info/RECORD
