Metadata-Version: 2.4
Name: library_and_tools
Version: 1.0.0
Summary: Ziad Library for drawing, reading files, and more. Enjoy!💝
Author: zeyad
Author-email: zeyad <zayedzezo82@gmail.com>
Requires-Python: >=3.7
Dynamic: author
